odoo/addons/stock_archive_constraint/README.rst
odoo/addons/stock_archive_constraint/__init__.py
odoo/addons/stock_archive_constraint/__manifest__.py
odoo/addons/stock_archive_constraint/i18n/es_ES.po
odoo/addons/stock_archive_constraint/i18n/stock_archive_constraint.pot
odoo/addons/stock_archive_constraint/models/__init__.py
odoo/addons/stock_archive_constraint/models/product_product.py
odoo/addons/stock_archive_constraint/models/product_template.py
odoo/addons/stock_archive_constraint/models/stock_location.py
odoo/addons/stock_archive_constraint/readme/CONTRIBUTORS.rst
odoo/addons/stock_archive_constraint/readme/DESCRIPTION.rst
odoo/addons/stock_archive_constraint/readme/USAGE.rst
odoo/addons/stock_archive_constraint/static/description/icon.png
odoo/addons/stock_archive_constraint/static/description/index.html
odoo/addons/stock_archive_constraint/tests/__init__.py
odoo/addons/stock_archive_constraint/tests/test_location_archive_constraint.py
odoo13_addon_stock_archive_constraint-13.0.1.0.1.dist-info/METADATA
odoo13_addon_stock_archive_constraint-13.0.1.0.1.dist-info/WHEEL
odoo13_addon_stock_archive_constraint-13.0.1.0.1.dist-info/top_level.txt
odoo13_addon_stock_archive_constraint-13.0.1.0.1.dist-info/RECORD
